cdef_utils/__init__.py
cdef_utils/__main__.py
cdef_utils/convert.py
cdef_utils/covariates.py
cdef_utils/education.py
cdef_utils/families.py
cdef_utils/lpr_link.py
cdef_utils-2.8.0.dist-info/METADATA
cdef_utils-2.8.0.dist-info/WHEEL
cdef_utils-2.8.0.dist-info/entry_points.txt
cdef_utils-2.8.0.dist-info/RECORD
