Metadata-Version: 2.3
Name: cdef-utils
Version: 2.8.0
Summary: Utility for converting CSV to Parquet files
Author-email: Tobias Kragholm <50784887+tkragholm@users.noreply.github.com>
License-Expression: MIT
Requires-Python: >=3.8
Requires-Dist: charset-normalizer>=3.3.2
Requires-Dist: polars[all]>=1.9.0
Requires-Dist: pyarrow>=17.0.0
Requires-Dist: pyreadr>=0.5.2
Requires-Dist: rich>=13.9.2
